fbmessenger/__init__.py
fbmessenger/attachments.py
fbmessenger/elements.py
fbmessenger/error_messages.py
fbmessenger/quick_replies.py
fbmessenger/sender_actions.py
fbmessenger/templates.py
fbmessenger/thread_settings.py
fbmessenger-5.6.0.dist-info/LICENSE.md
fbmessenger-5.6.0.dist-info/METADATA
fbmessenger-5.6.0.dist-info/WHEEL
fbmessenger-5.6.0.dist-info/top_level.txt
fbmessenger-5.6.0.dist-info/RECORD
